staff_view/__init__.py
staff_view/version.py
staff_view/views.py
staff_view/templates/staff_view.html
django_staff_view-1.0.3.dist-info/METADATA
django_staff_view-1.0.3.dist-info/WHEEL
django_staff_view-1.0.3.dist-info/top_level.txt
django_staff_view-1.0.3.dist-info/RECORD
