Metadata-Version: 2.1
Name: django-staff-view
Version: 1.0.3
Summary: Staff views for Django
Home-page: https://github.com/bboogaard/django-staff-view
Author: Bram Boogaard
Author-email: padawan@hetnet.nl
License: MIT License
Keywords: Django Staff views
Classifier: Development Status :: 3 - Alpha
Requires-Dist: pytest
Requires-Dist: pytest-cov
Requires-Dist: pytest-django >=4.5.2
Requires-Dist: django >=4.2.9
Requires-Dist: pyquery >=2.0.0
